EVCode/EVCLib.py
EVCode/__init__.py
EVCode-1.8.0.dist-info/LICENSE
EVCode-1.8.0.dist-info/METADATA
EVCode-1.8.0.dist-info/WHEEL
EVCode-1.8.0.dist-info/top_level.txt
EVCode-1.8.0.dist-info/RECORD
